MANIFEST.in
README.md
setup.py
gym_bci/__init__.py
gym_bci/_version.txt
gym_bci.egg-info/PKG-INFO
gym_bci.egg-info/SOURCES.txt
gym_bci.egg-info/dependency_links.txt
gym_bci.egg-info/requires.txt
gym_bci.egg-info/top_level.txt
gym_bci/__pycache__/__init__.cpython-38.pyc
gym_bci/envs/__init__.py
gym_bci/envs/__pycache__/__init__.cpython-38.pyc
gym_bci/envs/__pycache__/arrows_env.cpython-38.pyc
gym_bci/envs/__pycache__/bci_env.cpython-38.pyc
gym_bci/envs/__pycache__/foo_env.cpython-38.pyc
gym_bci/envs/__pycache__/test.cpython-38.pyc
gym_bci/envs/arrows/__init__.py
gym_bci/envs/arrows/arrows_env.py
gym_bci/envs/arrows/__pycache__/__init__.cpython-38.pyc
gym_bci/envs/arrows/__pycache__/arrows_env.cpython-38.pyc
gym_bci/envs/pacman/__init__.py
gym_bci/envs/pacman/game.py
gym_bci/envs/pacman/ghostAgents.py
gym_bci/envs/pacman/graphicsDisplay.py
gym_bci/envs/pacman/graphicsUtils.py
gym_bci/envs/pacman/layout.py
gym_bci/envs/pacman/pacman.py
gym_bci/envs/pacman/pacmanAgents.py
gym_bci/envs/pacman/pacman_env.py
gym_bci/envs/pacman/util.py
gym_bci/envs/pacman/__pycache__/__init__.cpython-38.pyc
gym_bci/envs/pacman/__pycache__/game.cpython-38.pyc
gym_bci/envs/pacman/__pycache__/ghostAgents.cpython-38.pyc
gym_bci/envs/pacman/__pycache__/graphicsDisplay.cpython-38.pyc
gym_bci/envs/pacman/__pycache__/graphicsUtils.cpython-38.pyc
gym_bci/envs/pacman/__pycache__/layout.cpython-38.pyc
gym_bci/envs/pacman/__pycache__/pacman.cpython-38.pyc
gym_bci/envs/pacman/__pycache__/pacmanAgents.cpython-38.pyc
gym_bci/envs/pacman/__pycache__/pacman_env.cpython-38.pyc
gym_bci/envs/pacman/__pycache__/util.cpython-38.pyc
gym_bci/envs/pacman/layouts/__init__.py
gym_bci/envs/pacman/layouts/capsuleClassic.lay
gym_bci/envs/pacman/layouts/capsuleClassic_noGhosts.lay
gym_bci/envs/pacman/layouts/contestClassic.lay
gym_bci/envs/pacman/layouts/contestClassic_noGhosts.lay
gym_bci/envs/pacman/layouts/mediumClassic.lay
gym_bci/envs/pacman/layouts/mediumClassic_noGhosts.lay
gym_bci/envs/pacman/layouts/mediumGrid.lay
gym_bci/envs/pacman/layouts/mediumGrid_noGhosts.lay
gym_bci/envs/pacman/layouts/minimaxClassic.lay
