Metadata-Version: 1.2
Name: gym-bci
Version: 0.3
Summary: GCPDS: gym-bci
Home-page: UNKNOWN
Author: Yeison Cardona
Author-email: yeisoneng@gmail.com
Maintainer: Yeison Cardona
Maintainer-email: yeisoneng@gmail.com
License: BSD License
Download-URL: https://bitbucket.org/gcpds/gym_bci/downloads/
Platform: UNKNOWN
